folding/__init__.py
folding/alphafold/__init__.py
folding/alphafold/models.py
folding/alphafold/msa.py
folding/batch.py
folding/citations.py
folding/colabfold.py
folding/core/__init__.py
folding/core/features.py
folding/core/msa.py
folding/core/prediction.py
folding/data/__init__.py
folding/data/templates.py
folding/download.py
folding/main.py
folding/mmseqs/__init__.py
folding/mmseqs/merge_and_split_msas.py
folding/mmseqs/search.py
folding/mmseqs/split_msas.py
folding/models/__init__.py
folding/models/model_runner.py
folding/openstructure/LGPL.txt
folding/openstructure/README.md
folding/openstructure/stereo_chemical_props.txt
folding/pdb.py
folding/plot.py
folding/relax.py
folding/utils/__init__.py
folding/utils/common.py
folding/utils/file_management.py
folding/visualization/__init__.py
folding/visualization/plots.py
folding-0.0.5.dist-info/LICENSE
folding-0.0.5.dist-info/METADATA
folding-0.0.5.dist-info/WHEEL
folding-0.0.5.dist-info/entry_points.txt
folding-0.0.5.dist-info/RECORD
