Metadata-Version: 2.1
Name: folding
Version: 0.0.5
Summary: ColabFold modified for AlphaFold2 and local installation
Home-page: https://github.com/truemagic-coder/cyberchipped-fold
License: MIT, but separate licenses for the trained weights
Author: Bevan Hunt
Requires-Python: >=3.9,<3.12
Classifier: License :: Other/Proprietary License
Classifier: Programming Language :: Python :: 3
Classifier: Programming Language :: Python :: 3.9
Classifier: Programming Language :: Python :: 3.10
Classifier: Programming Language :: Python :: 3.11
Classifier: Topic :: Scientific/Engineering :: Artificial Intelligence
Classifier: Topic :: Scientific/Engineering :: Bio-Informatics
Provides-Extra: alphafold
Provides-Extra: alphafold-minus-jax
Requires-Dist: absl-py (>=1.0.0,<2.0.0)
Requires-Dist: alphafold-colabfold (==v2.3.6) ; extra == "alphafold" or extra == "alphafold-minus-jax"
Requires-Dist: appdirs (>=1.4.4,<2.0.0)
Requires-Dist: biopython (<1.83)
Requires-Dist: dm-haiku (>=0.0.12,<0.0.13)
Requires-Dist: importlib-metadata (>=4.8.2,<5.0.0)
Requires-Dist: jax (>=0.4.20,<0.5.0) ; extra == "alphafold"
Requires-Dist: matplotlib (>=3.2.2,<4.0.0)
Requires-Dist: numpy (>=1.22.0,<2.0.0)
Requires-Dist: pandas (>=1.3.4,<2.0.0)
Requires-Dist: py3Dmol (>=2.0.1,<3.0.0)
Requires-Dist: requests (>=2.32.3,<3.0.0)
Requires-Dist: tensorflow-cpu (>=2.12.1,<3.0.0) ; sys_platform != "darwin"
Requires-Dist: tensorflow-macos (<2.14.0) ; sys_platform == "darwin"
Requires-Dist: torch
Requires-Dist: tqdm (>=4.62.2,<5.0.0)
Project-URL: Repository, https://github.com/truemagic-coder/cyberchipped-fold
